{"Audi": {"head": "Audi A6 50 TDI quattro: nemir v premijskem razredu", "author": "Miha Merljak", "datetime": "\n\t\t28. december 2018 ob 08:51", "subtitle": "Test nove generacije", "leader": "To je novi audi A6. V razred najdrazjih in najbolj premijskih zrebcev je vnesel nemir, se preden je sploh zapeljal na parkirni prostor, rezerviran za izvrsnega direktorja. ", "content": "\n\n\t\t\t\n\t\t\t\t\n\n\t\n\t\t\n\t\t\t\n\t\t\n\t\t\n\t\t\t\n\t\t\t\tAudi A6 je avtomobil za direktorje, ki se mu na avtocesti spostljivo umikajo, kot bi slo za Pahorjev ali Sarcev avtomobil. Foto: David Savli\t\t\t\n\t\t\t\n\n\t\t\t\n\t\t\t\n\t\t\t\n\n\t\t\t\t\n\n\tOglas\n\t\n\t\n\t\n\t\n\n\n\n\n\n\n\n\t\t\t\t\t\n\t\t\t\t\n\t\t\n\n\t\t\t\t\n\n\t\t\t\t\nSamo poglejte njegovo masko  to ogromno satovje z radarji na takem polozaju, da se ti na avtocesti tudi pri 120 km/h vsi spostljivo umikajo, saj so prepricani, da gre za Pahorjev ali Sarcev avto. Seveda, novi A6 lahko cesto in promet skenira s kar petimi radarji, petimi kamerami, infrardeco kamero za nocni vid, dvanajstimi ultrazvocnimi senzorji in laserskim citalnikom  lidarjem. V glavnem vojaska tehnologija v sluzbi varnosti za fante, ki smo radi gledali Top Gun, Bonda in druge mozakarja s finimi igracami.Novo poglavjeVozniski delovni prostor je novo poglavje digitalne dobe, z dvema ogromnima zaslonoma, ki tako kot naprednejsi telefoni dregnejo blazinice vasih prstov, kot se sprehajate po steklu. A se bolj se nam zdi pomembno, da so osnovna stikala tam, kjer jih pricakujete. Najprej so torej zagotovili enostavno osnovo, tisti bolj \"advanced\" vozniki pa si lahko nato vse skupaj se veliko bolj prilagodijo. Velik korak naprej pri kabinskem udobju zaznavajo tudi na zadnji klopi, tam je prostora v vseh smereh precej vec.Ce vam pogled na Audijev spisek dodatne opreme ne odvzame volje do zivljenja, potem vsekakor toplo priporocamo nakup zracnega vzmetenja, saj dobi z njim A6 vec razlicnih in voznisko zelo uporabnih karakterjev.Enako velja za seksi luci z inteligentno matricno osvetlitvijo, pa za sportno podvozje in vsekakor za stirikolesno krmiljenje. S tem postane A6 med ovinki v obcutku na volanu se veliko krajsi in bolj agilen. Vse nasteto smo preskusali v druzbi agregata 50 TDI, ki je v resnici klasicni trilitrski dizel, podkrepljen z elektromotorjem. Ja, ta audi je mehki hibrid z izjemnim navorom in dovolj moci kadar koli in kjer koli. Si pa mislimo, da bo najvecji del trga zadovoljil ze ucinkovit dvolitrski mehki hibrid z mocjo 150 kilovatov.Kljucni tehnicni podatki:- na testu Audi A6 50 TDI quattro tiptronicMere:- dolzina: 4,9 m- medosna razdalja: 2,9 m- obracalni krog: 12,1 m- prtljaznik: 530 l- masa: 1.900 kgPogon:- trilitrski sestvaljni dizelski motor- moc: 210 kW- navor: 620 Nm- 8-stopenjski samodejni menjalnik- pogon na vsa stiri kolesa- pnevmatike: 225/60 R17- poraba: 6,6 l/100 km = 8,9 EUR/100 km- posoda za gorivo: 73 l- doseg: 1.106 km- izpusti CO2: 147 g/kmStroski pri 15.000 km in 5-letni uporabi:- nakupna cena: 69.080 EUR- stroski financnega lizinga: 4.463 EUR/5 let- stroski registracije: 10.829 EUR/5 let- stroski vzdrzevanja: 1.926 EUR/5 let- stroski goriva: 6.702 EUR/75.000 km- strosek 1 kompleta pnevmatik: 716 EUR- vrednosti po 5 letih po Eurotaxu: 33.964 EUR- stroski skupaj: 1.001 EUR/mesec\n\n\n\n\n\n\n\n\n\n\t\t\t\t\n\n\n\n\n\n\n\n\n\n\t\t\t\t\n\t\t\t\t\n\t\n\t\n\t\t\n\t\t\t\n\t\t\t\t\n\t\t\t\t\t\t\t\t\t\n\t\t\t\t\t\n\t\t\t\t\t\n\t\t\t\t\t\t\n\t\t\t\t\t\t\t\n\t\t\t\t\t\t\t\t\n\t\t\t\t\t\t\t\n\t\t\t\t\t\t\tMMC RTV SLO \n\t\t\t\t\t\t\n\t\t\t\t\t\t\t\t\t\t\t\t\t\t\n\t\t\t\t\t\n\t\t\t\t\t\n\t\t\t\t\t\t\n\t\t\t\t\t\t\t\n\t\t\t\t\t\t\t\t\n\t\t\t\t\t\t\t\n\t\t\t\t\t\t\tMMC RTV SLO \n\t\t\t\t\t\t\n\t\t\t\t\t\t\t\t\t\t\t\t\t\t\n\t\t\t\t\t\n\t\t\t\t\t\n\t\t\t\t\t\t\n\t\t\t\t\t\t\t\n\t\t\t\t\t\t\t\t\n\t\t\t\t\t\t\t\n\t\t\t\t\t\t\tMMC RTV SLO \n\t\t\t\t\t\t\n\t\t\t\t\t\t\t\t\t\t\t\t\t\t\n\t\t\t\t\t\n\t\t\t\t\t\n\t\t\t\t\t\t\n\t\t\t\t\t\t\t\n\t\t\t\t\t\t\t\t\n\t\t\t\t\t\t\t\n\t\t\t\t\t\t\tMMC RTV SLO \n\t\t\t\t\t\t\n\t\t\t\t\t\t\t\t\t\t\t\t\t\t\n\t\t\t\t\t\n\t\t\t\t\t\n\t\t\t\t\t\t\n\t\t\t\t\t\t\t\n\t\t\t\t\t\t\t\t\n\t\t\t\t\t\t\t\n\t\t\t\t\t\t\tMMC RTV SLO \n\t\t\t\t\t\t\n\t\t\t\t\t\t\t\t\t\t\t\t\t\t\n\t\t\t\t\t\n\t\t\t\t\t\n\t\t\t\t\t\t\n\t\t\t\t\t\t\t\n\t\t\t\t\t\t\t\t\n\t\t\t\t\t\t\t\n\t\t\t\t\t\t\tMMC RTV SLO \n\t\t\t\t\t\t\n\t\t\t\t\t\t\t\t\t\t\t\t\t\t\n\t\t\t\t\t\n\t\t\t\t\t\n\t\t\t\t\t\t\n\t\t\t\t\t\t\t\n\t\t\t\t\t\t\t\t\n\t\t\t\t\t\t\t\n\t\t\t\t\t\t\tV notranjosti kraljujejo zasloni, prek katerih je mogoce upravljati prakticno vse funkcije avtomobila. Foto: David Savli\n\t\t\t\t\t\t\n\t\t\t\t\t\t\t\t\t\t\t\t\t\t\n\t\t\t\t\t\n\t\t\t\t\t\n\t\t\t\t\t\t\n\t\t\t\t\t\t\t\n\t\t\t\t\t\t\t\t\n\t\t\t\t\t\t\t\n\t\t\t\t\t\t\tMMC RTV SLO \n\t\t\t\t\t\t\n\t\t\t\t\t\t\t\t\t\t\t\t\t\t\n\t\t\t\t\t\n\t\t\t\t\t\n\t\t\t\t\t\t\n\t\t\t\t\t\t\t\n\t\t\t\t\t\t\t\t\n\t\t\t\t\t\t\t\n\t\t\t\t\t\t\tMMC RTV SLO \n\t\t\t\t\t\t\n\t\t\t\t\t\t\t\t\t\t\t\t\t\t\n\t\t\t\t\t\n\t\t\t\t\t\n\t\t\t\t\t\t\n\t\t\t\t\t\t\t\n\t\t\t\t\t\t\t\t\n\t\t\t\t\t\t\t\n\t\t\t\t\t\t\tMMC RTV SLO \n\t\t\t\t\t\t\n\t\t\t\t\t\t\t\t\t\t\t\t\t\t\n\t\t\t\t\t\n\t\t\t\t\t\n\t\t\t\t\t\t\n\t\t\t\t\t\t\t\n\t\t\t\t\t\t\t\t\n\t\t\t\t\t\t\t\n\t\t\t\t\t\t\tMMC RTV SLO \n\t\t\t\t\t\t\n\t\t\t\t\t\t\t\t\t\t\t\t\t\t\n\t\t\t\t\t\n\t\t\t\t\t\n\t\t\t\t\t\t\n\t\t\t\t\t\t\t\n\t\t\t\t\t\t\t\t\n\t\t\t\t\t\t\t\n\t\t\t\t\t\t\tMMC RTV SLO \n\t\t\t\t\t\t\n\t\t\t\t\t\t\t\t\t\t\t\t\t\t\n\t\t\t\t\t\n\t\t\t\t\t\n\t\t\t\t\t\t\n\t\t\t\t\t\t\t\n\t\t\t\t\t\t\t\t\n\t\t\t\t\t\t\t\n\t\t\t\t\t\t\tMed doplacili priporocamo zracno vzmetenje in stirikolesno krmiljenje. Foto: David Savli\n\t\t\t\t\t\t\n\t\t\t\t\t\t\t\t\t\t\t\t\t\t\n\t\t\t\t\t\n\t\t\t\t\t\n\t\t\t\t\t\t\n\t\t\t\t\t\t\t\n\t\t\t\t\t\t\t\t\n\t\t\t\t\t\t\t\n\t\t\t\t\t\t\tMMC RTV SLO \n\t\t\t\t\t\t\n\t\t\t\t\t\t\t\t\t\t\t\t\t\t\n\t\t\t\t\t\n\t\t\t\t\t\n\t\t\t\t\t\t\n\t\t\t\t\t\t\t\n\t\t\t\t\t\t\t\t\n\t\t\t\t\t\t\t\n\t\t\t\t\t\t\tMMC RTV SLO \n\t\t\t\t\t\t\n\t\t\t\t\t\t\t\t\t\t\t\t\t\t\n\t\t\t\t\t\n\t\t\t\t\t\n\t\t\t\t\t\t\n\t\t\t\t\t\t\t\n\t\t\t\t\t\t\t\t\n\t\t\t\t\t\t\t\n\t\t\t\t\t\t\tMMC RTV SLO \n\t\t\t\t\t\t\n\t\t\t\t\t\t\t\t\t\t\t\t\t\t\n\t\t\t\t\t\n\t\t\t\t\t\n\t\t\t\t\t\t\n\t\t\t\t\t\t\t\n\t\t\t\t\t\t\t\t\n\t\t\t\t\t\t\t\n\t\t\t\t\t\t\tMMC RTV SLO \n\t\t\t\t\t\t\n\t\t\t\t\t\t\t\t\t\t\t\t\t\t\n\t\t\t\t\t\n\t\t\t\t\t\n\t\t\t\t\t\t\n\t\t\t\t\t\t\t\n\t\t\t\t\t\t\t\t\n\t\t\t\t\t\t\t\n\t\t\t\t\t\t\tMMC RTV SLO \n\t\t\t\t\t\t\n\t\t\t\t\t\t\t\t\t\t\t\t\t\t\n\t\t\t\t\t\n\t\t\t\t\t\n\t\t\t\t\t\t\n\t\t\t\t\t\t\t\n\t\t\t\t\t\t\t\t\n\t\t\t\t\t\t\t\n\t\t\t\t\t\t\tMMC RTV SLO \n\t\t\t\t\t\t\n\t\t\t\t\t\t\t\t\t\t\t\t\n\t\t\t\n\t\t\t\n\t\t\n\t\t\n\t\t\t\t\t\t\t\t\t\t\n\t\t\t\t\n\t\t\t\t\t\n\t\t\t\t\t\t\n\t\t\t\t\t\t\t\n\t\t\t\t\t\t\n\t\t\t\t\t\tMMC RTV SLO \n\t\t\t\t\t\n\t\t\t\t\t\t\t\t\t\t\t\t\n\t\t\t\t\n\t\t\t\t\t\n\t\t\t\t\t\t\n\t\t\t\t\t\t\t\n\t\t\t\t\t\t\n\t\t\t\t\t\tMMC RTV SLO \n\t\t\t\t\t\n\t\t\t\t\t\t\t\t\t\t\t\t\n\t\t\t\t\n\t\t\t\t\t\n\t\t\t\t\t\t\n\t\t\t\t\t\t\t\n\t\t\t\t\t\t\n\t\t\t\t\t\tMMC RTV SLO \n\t\t\t\t\t\n\t\t\t\t\t\t\t\t\t\t\t\t\n\t\t\t\t\n\t\t\t\t\t\n\t\t\t\t\t\t\n\t\t\t\t\t\t\t\n\t\t\t\t\t\t\n\t\t\t\t\t\tMMC RTV SLO \n\t\t\t\t\t\n\t\t\t\t\t\t\t\t\t\t\t\t\t\t\t\t\t\t\t\t\t\t\t\t\t\t\t\t\t\t\t\t\t\t\t\t\t\t\t\t\t\t\t\t\t\t\t\t\t\t\t\t\t\t\t\t\t\t\t\t\t\t\t\t\t\t\t\t\t\t\t\t\t\t\t\t\t\t\t\t\t\n\t\n\n\t\t\t\n\t\t\n\n\t\t"}, "Volvo": {"head": "Volvo XC 40 D4 AWD momentum: suvereno med najboljse v razredu", "author": "Miha Merljak", "datetime": "\n\t\t25. januar 2019 ob 15:23", "subtitle": "Test novega modela", "leader": "XC 40 je najmanjsi Volvov SUV, ki se oblikovno skoraj v celotni naslanja na oba vecja predhodnika. Ze samo s tem so mu vrata do denarnic tistih kupcev, ki iscejo izstopajoco, a hkrati visoko kultivirano in precisceno dizajnersko govorico, na pol odprta.", "content": "\n\t\t\t\n\t\t\t\n\t\t\t\t\n\t\t\n\n\t\t\t\t\t\t\n\t\t\t\t\t\t\n\t\t\t\n\t\t\t\t\n\n\t\t\t\t\t\t\t\t\t\n\t\t\t\t\t\t\t\t\t\t\n\t\t\t\t\t\t\t\t\t\n\t\t\t\t\t\t\t\t\t\n\t\t\t\t\t\t\t\t\t\tXC40 se v mestu odlicno zlije z okolico. Foto: David Savli\n\t\t\t\t\t\t\t\t\t\n\t\t\t\t\t\t\t\t\n\t\t\t\t\t\t\n\t\t\t\t\t\n\n\n\nVolvo se je nizjih srednjih razredov v preteklosti izogibal ali pa je vanje vstopal z zelo nisnimi produkti, ki niso pustili vecjega trznega pecata. V primeru XC 40 ni tezko napovedati, da bo ta tradicija prekinjena. Ponuja namrec visoko kakovost koncne izdelave in v kabini odlicno premisljeno funkcionalnost ter na dotik prijetne materiale. Se posebej hvalimo stevilo, iznajdljivost in velikost razlicnih odlagalnih prostorov ter siroke, cvrste in zelo udobne sedeze. Intuitivno in enostavno logicno je upravljanje z velikim vmesnikom, ki z vecfunkcijskim zaslonom na dotik kraljuje na z roko lahko dostopnem mestu na sredinski armaturi. Razocaranj ne bo niti v velikosti in uporabnosti prtljaznega prostora, ki s 460 litri prostornine sicer ni med vecjimi v razredu, a se v uporabniskem smislu odkupi z dobro urejenostjo ter domiselnimi resitvami pregrajevanja.\n\t\t\t\t\t\t\t\t\t\n\t\t\t\t\t\t\t\t\t\t\n\t\t\t\t\t\t\t\t\t\n\t\t\t\t\t\t\t\t\t\n\t\t\t\t\t\t\t\t\t\tFoto: David Savli\n\t\t\t\t\t\t\t\t\t\n\t\t\t\t\t\t\t\tXC 40 je od tal odmaknjen konkretnih 21 cm, a sta vzmetenje in krmilni mehanizem tako nastavljena, da ponuja tudi v hitro odpeljanih ovinkih zelo dolgo nevtralno in predvidljivo lego. V premeru preskusanega modela, ki je imel v paketu R design vzmetenje se nekoliko bolj trdo, se je to samo se bolj potrdilo, a je v tem primeru treba racunati na manj udobno voznjo cez razlicne asfaltne grbine. Podoben razmislek velja opraviti tudi pri izbiri motorja.Preskusani 2-litrski dizel s 190 KM predstavlja vrh ponudbe, ki z mocjo, udobjem in tudi povprecno porabo navdusi predvsem pri avtocestnih dolgoprogaskih izzivih, v pocasni mestni voznji ter pri pogostih postankih in speljevanjih pa deluje prevec robusten.XC 40 je s cvrsto gradnjo, funkcionalno in udobno kabino ter stevilnimi asistencnimi sistemi in izstopajocim skandinavskim dizajnom v premisljenem trenutku vstopil na trg modnih mestnih terencev, v katerem se brez ene same sence dvoma suvereno postavi med najdrazje in najbolj premijske v mestu.Kljucni tehnicni podatki:- na testu Volvo XC40 2.0 TD avt awd momentumMere:- dolzina: 4,4 m- medosna razdalja: 2,7 m- obracalni krog: 11,4 m- oddaljenost od tal: 21 cm- prtljaznik: 432 l- masa: 2.250 kgPogon:- 2-litrski 4-valjni bencinski motor- moc: 140 kW- navor: 400 Nm- 8-stopenjski samodejni menjalnik- pogon na vsa stiri kolesa- pnevmatike: 235/50 R19 - poraba: 6,3 l/100 km = 8,2 EUR/100km- posoda za gorivo: 54 l- doseg: 857 km- izpusti CO2: 133 g/kmStroski pri 15.000 km in 5-letni uporabi:- nakupna cena: 43.619 EUR- stroski financnega leasinga: 3.268 EUR/5 let- stroski registracije: 8.701 EUR/5 let- stroski vzdrzevanja: 2.320 EUR/5 let- stroski goriva: 6.190 EUR/75.000 km- strosek 1 kompleta pnevmatik: 923 EUR- vrednosti po 5 letih po Eurotaxu: 18.886 EUR- stroski skupaj: 774 EUR/mesec\n\t\t\t\t\t\t\t\t\n\t\t\t\t\t\t\t\t\t\n\t\t\t\t\t\t\t\t\n\t\t\t\t\t\t\t\n\n\t\t\t\t\t\n\t\t\t\t\t\t\n\t\t\t\n\t\t\t\t\t\n\t\t\t\t\t\t\n\t\t\t\t\t\t\t\n\t\t\t\t\t\t\n\t\t\t\t\t\t Foto: David Savli\n\t\t\t\t\t\n\t\t\t\t\n\t\t\t\t\t\n\t\t\t\t\t\t\n\t\t\t\t\t\t\t\n\t\t\t\t\t\t\n\t\t\t\t\t\t Foto: David Savli\n\t\t\t\t\t\n\t\t\t\t\n\t\t\t\t\t\n\t\t\t\t\t\t\n\t\t\t\t\t\t\t\n\t\t\t\t\t\t\n\t\t\t\t\t\t Foto: David Savli\n\t\t\t\t\t\n\t\t\t\t\n\t\t\t\t\t\n\t\t\t\t\t\t\n\t\t\t\t\t\t\t\n\t\t\t\t\t\t\n\t\t\t\t\t\t Foto: David Savli\n\t\t\t\t\t\n\t\t\t\t\n\t\t\t\t\t\n\t\t\t\t\t\t\n\t\t\t\t\t\t\t\n\t\t\t\t\t\t\n\t\t\t\t\t\t Foto: David Savli\n\t\t\t\t\t\n\t\t\t\t\n\t\t\t\t\t\n\t\t\t\t\t\t\n\t\t\t\t\t\t\t\n\t\t\t\t\t\t\n\t\t\t\t\t\t Foto: David Savli\n\t\t\t\t\t\n\t\t\t\t\n\t\t\t\t\t\n\t\t\t\t\t\t\n\t\t\t\t\t\t\t\n\t\t\t\t\t\t\n\t\t\t\t\t\t Foto: David Savli\n\t\t\t\t\t\n\t\t\t\t\n\t\t\t\t\t\n\t\t\t\t\t\t\n\t\t\t\t\t\t\t\n\t\t\t\t\t\t\n\t\t\t\t\t\t Foto: David Savli\n\t\t\t\t\t\n\t\t\t\t\n\t\t\t\t\t\n\t\t\t\t\t\t\n\t\t\t\t\t\t\t\n\t\t\t\t\t\t\n\t\t\t\t\t\t Foto: David Savli\n\t\t\t\t\t\n\t\t\t\t\n\t\t\t\t\t\n\t\t\t\t\t\t\n\t\t\t\t\t\t\t\n\t\t\t\t\t\t\n\t\t\t\t\t\t Foto: David Savli\n\t\t\t\t\t\n\t\t\t\t\n\t\t\t\t\t\n\t\t\t\t\t\t\n\t\t\t\t\t\t\t\n\t\t\t\t\t\t\n\t\t\t\t\t\t Foto: David Savli\n\t\t\t\t\t\n\t\t\t\t\n\t\t\t\t\t\n\t\t\t\t\t\t\n\t\t\t\t\t\t\t\n\t\t\t\t\t\t\n\t\t\t\t\t\t Foto: David Savli\n\t\t\t\t\t\n\t\t\t\t\n\t\t\t\t\t\n\t\t\t\t\t\t\n\t\t\t\t\t\t\t\n\t\t\t\t\t\t\n\t\t\t\t\t\t Foto: David Savli\n\t\t\t\t\t\n\t\t\t\t\n\t\t\t\t\t\n\t\t\t\t\t\t\n\t\t\t\t\t\t\t\n\t\t\t\t\t\t\n\t\t\t\t\t\t Foto: David Savli\n\t\t\t\t\t\n\t\t\t\t\n\t\t\t\t\t\n\t\t\t\t\t\t\n\t\t\t\t\t\t\t\n\t\t\t\t\t\t\n\t\t\t\t\t\t Foto: David Savli\n\t\t\t\t\t\n\t\t\t\t\n\t\t\t\t\t\n\t\t\t\t\t\t\n\t\t\t\t\t\t\t\n\t\t\t\t\t\t\n\t\t\t\t\t\t Foto: David Savli\n\t\t\t\t\t\n\t\t\t\t\n\t\t\t\t\t\n\t\t\t\t\t\t\n\t\t\t\t\t\t\t\n\t\t\t\t\t\t\n\t\t\t\t\t\t Foto: David Savli\n\t\t\t\t\t\n\t\t\t\t\n\t\t\t\t\t\n\t\t\t\t\t\t\n\t\t\t\t\t\t\t\n\t\t\t\t\t\t\n\t\t\t\t\t\t Foto: David Savli\n\t\t\t\t\t\n\t\t\t\t\n\t\t\t\t\n\t\t\t\t\n\t\t\t\t\n\t\t\t\n\t\t\t\n\t\t\t\n\t\t\t\t\t\t\t\t\t\n\t\t\t\t\t\t\t\t\t\t\n\t\t\t\t\t\t\t\t\t\n\t\t\t\t\t\t\t\t\t Foto: David Savli\n\t\t\t\t\t\t\t\t\n\t\t\t\t\t\t\t\t\t\n\t\t\t\t\t\t\t\t\t\t\n\t\t\t\t\t\t\t\t\t\n\t\t\t\t\t\t\t\t\t Foto: David Savli\n\t\t\t\t\t\t\t\t\n\t\t\t\t\t\t\t\t\t\n\t\t\t\t\t\t\t\t\t\t\n\t\t\t\t\t\t\t\t\t\n\t\t\t\t\t\t\t\t\t Foto: David Savli\n\t\t\t\t\t\t\t\t\n\t\t\t\t\t\t\t\t\t\n\t\t\t\t\t\t\t\t\t\t\n\t\t\t\t\t\t\t\t\t\n\t\t\t\t\t\t\t\t\t Foto: David Savli\n\t\t\t\t\t\t\t\t\n\t\t\t\t\n\t\t\t\n\n\t\t\t\n\t\t\n\t\t\n\t\t"}}